memobj/__init__.py
memobj/allocation.py
memobj/hook.py
memobj/object.py
memobj/process/__init__.py
memobj/process/base.py
memobj/process/module.py
memobj/process/windows/__init__.py
memobj/process/windows/module.py
memobj/process/windows/process.py
memobj/process/windows/utils.py
memobj/property/__init__.py
memobj/property/array.py
memobj/property/base.py
memobj/property/pointer.py
memobj/property/simple.py
memobj/property/string.py
memobj/utils.py
memobj-0.16.0.dist-info/WHEEL
memobj-0.16.0.dist-info/METADATA
memobj-0.16.0.dist-info/RECORD
