Metadata-Version: 2.4
Name: memobj
Version: 0.16.0
Summary: A library for defining objects in memory
Author: StarrFox
Author-email: StarrFox <starrfox6312@gmail.com>
License-Expression: MIT
Requires-Dist: iced-x86>=1.21.0
Requires-Dist: pefile>=2024.8.26 ; sys_platform == 'win32'
Requires-Dist: regex>=2025.9.18
Requires-Python: >=3.11
Project-URL: Issues, https://github.com/StarrFox/memobj/issues
Project-URL: Repository, https://github.com/StarrFox/memobj
